ratio/__init__.py
ratio/application/__init__.py
ratio/application/application.py
ratio/application/discover_routes.py
ratio/application/load_local_module.py
ratio/authentication/__init__.py
ratio/authentication/basic_authentication.py
ratio/database/__init__.py
ratio/database/fields/__init__.py
ratio/database/migrations/__init__.py
ratio/database/models/__init__.py
ratio/database/seeders/__init__.py
ratio/http/__init__.py
ratio/http/headers.py
ratio/http/parameters.py
ratio/http/request.py
ratio/http/response.py
ratio/router/__init__.py
ratio/router/exceptions.py
ratio/router/is_route.py
ratio/router/redirect.py
ratio/router/resolvers/__init__.py
ratio/router/resolvers/direct_resolver.py
ratio/router/resolvers/dynamic_resolver.py
ratio/router/resolvers/generic_routes.py
ratio/router/resolvers/resolver.py
ratio/router/resolvers/util.py
ratio/router/route.py
ratio/router/route_path.py
ratio/router/route_type.py
ratio/router/router.py
ratio/util/__init__.py
ratio/util/remove_none.py
ratio-0.4.0.dist-info/LICENSE.md
ratio-0.4.0.dist-info/WHEEL
ratio-0.4.0.dist-info/METADATA
ratio-0.4.0.dist-info/RECORD
