Metadata-Version: 2.1
Name: ratio
Version: 0.4.0
Summary: The Python Web Framework for developers who like to get shit done
Author: Job Veldhuis
Author-email: job@baukefrederik.me
Requires-Python: >=3.11,<4.0
Classifier: Programming Language :: Python :: 3
Classifier: Programming Language :: Python :: 3.11
Requires-Dist: rich (>=12.6.0,<13.0.0)
